fugle_realtime/__init__.py
fugle_realtime/intraday.py
fugle_realtime_revision-0.2.9.dist-info/METADATA
fugle_realtime_revision-0.2.9.dist-info/WHEEL
fugle_realtime_revision-0.2.9.dist-info/top_level.txt
fugle_realtime_revision-0.2.9.dist-info/RECORD
