Metadata-Version: 2.1
Name: fugle-realtime-revision
Version: 0.2.9
Summary: Fugle Realtime Python is a Python package to query realtime stock quote of Taiwan market through API provided by Fugle.
Home-page: https://github.com/taiwan-tradingview/fugle_realtime_revision
Author: KB
Author-email: taiwan.tradingview@gmail.com
License: MIT
Platform: UNKNOWN
Classifier: License :: OSI Approved :: MIT License
Classifier: Programming Language :: Python
Classifier: Programming Language :: Python :: 3
Classifier: Programming Language :: Python :: 3.6
Classifier: Programming Language :: Python :: Implementation :: CPython
Classifier: Programming Language :: Python :: Implementation :: PyPy
Requires-Python: >=3.7.0
Requires-Dist: certifi (==2019.3.9)
Requires-Dist: chardet (==3.0.4)
Requires-Dist: idna (==2.8)
Requires-Dist: numpy (==1.21.1)
Requires-Dist: pandas (==1.3.1)
Requires-Dist: python-dateutil (==2.8.0)
Requires-Dist: pytz (==2019.1)
Requires-Dist: requests (==2.22.0)
Requires-Dist: six (==1.12.0)
Requires-Dist: urllib3 (==1.25.3)
